{
  "_help_Name": "Descriptive name of the TMeasy tire model",
  "Name": "Sedan TMeasy Tire",
  "Type": "Tire",
  "Template": "TMeasyTire",

  "_help_Design": "Design parameters for tire dimensions, rim size, and mass/inertia properties",
  "Design": {
    "Unloaded Radius [m]": 0.3266,
    "Mass [kg]": 11.5,
    "Inertia [kg.m2]": [ 0.156, 0.679, 0.156 ],
    "Width [m]": 0.245,
    "Rim Radius [m]": 0.2286
  },

  "_help_Friction": "Reference ground coefficient of friction",
  "Coefficient of Friction": 0.8,

  "_help_RollingResistance": "Tire rolling resistance coefficient",
  "Rolling Resistance Coefficient": 0.015,

  "_help_InflationPressure": "Optional: Inflation pressure at design and use state in Pa (if both design/use are set, they scale stiffness/forces)",
  "Inflation Pressure Design [Pa]": 220000.0,
  "Inflation Pressure Use [Pa]": 220000.0,

  "_help_LoadIndex": "Tire load index code. Together with 'Vehicle Type', it allows TMeasy to estimate vertical/longitudinal/lateral tire curves automatically.",
  "Vehicle Type": "Passenger",
  "Load Index": 97,

  "_help_BearingCapacity": "Optional: Maximum bearing capacity in Newtons. Used if Load Index is omitted.",
  "Maximum Bearing Capacity [N]": 10000,

  "_help_Visualization": "Mesh files for left and right tire rendering",
  "Visualization": {
    "Mesh Filename Left": "vehicle/sedan/sedan_tire.obj",
    "Mesh Filename Right": "vehicle/sedan/sedan_tire.obj"
  }
}
